submit50/__init__.py
submit50/__main__.py
submit50/locale/es/LC_MESSAGES/submit50.mo
submit50/locale/es/LC_MESSAGES/submit50.po
submit50-3.1.5.dist-info/LICENSE
submit50-3.1.5.dist-info/METADATA
submit50-3.1.5.dist-info/WHEEL
submit50-3.1.5.dist-info/entry_points.txt
submit50-3.1.5.dist-info/top_level.txt
submit50-3.1.5.dist-info/RECORD
